Metadata-Version: 2.1
Name: Sentip
Version: 1.0.0
Summary: Thai Social Data Sentiment Analysis
Home-page: https://github.com/hhej/Sentip
Author: Panjapol Ampornratana
Author-email: panjapol.pol@gmail.com
License: UNKNOWN
Keywords: NLP,THAI
Platform: UNKNOWN
Classifier: Natural Language :: Thai
Classifier: Programming Language :: Python :: 3.7
Classifier: License :: OSI Approved :: GNU General Public License v3 (GPLv3)
Requires-Python: >=3.7
